{"address": [["Hochschule f\u00fcr Evangelische Kirchenmusik", "Wilhelminenstra\u00dfe 9", "95444", "Bayreuth", "+49 (0)921/75934-17", "http://hfk-bayreuth.de"]], "id": 468, "studycheck": "/hochschulen/hfk-bayreuth", "studcheck_rating": [], "name": "Hochschule f\u00fcr Evangelische Kirchenmusik", "comments": [], "studiengaenge": [["Bl\u00e4serchorleitung/Blechblasinstrument", "Diplom"], ["Dirigieren (Chorleitung)", "Chorleitung"], ["Evangelische Kirchenmusik B", "Diplom"], ["Gottesdienstliches Orgelspiel/Improvisation", "Diplom"], ["Kirchenmusikalische A- Pr\u00fcfung", "Abschlusspr\u00fcfung"], ["Klavier", "Diplom"], ["Musikalische Fr\u00fcherziehung/Kinderchorleitung", "Diplom"], ["Orgel", "Diplom"], ["Popularmusik", "Diplom"]]}