{"address": [["Hochschule f\u00fcr angewandte P\u00e4dagogik", "Ostendstra\u00dfe 1", "12459", "Berlin", "+49 (0)30 20 60 89-0", "http://hsap.de"]], "id": 305, "studycheck": "/hochschulen/hsap", "studcheck_rating": [["5.0", "4.0", "4.0", "3.0", "5.0", "5.0", "4.3"]], "name": "Hochschule f\u00fcr angewandte P\u00e4dagogik", "comments": [["Man geht jeden Tag mit einem L\u00e4cheln aus der Universit\u00e4t. :) Die Inhalte sind ansprechend und die Dozenten f\u00f6rdern vor allem ein angenehmes Miteinander. Alle achten aufeinander und man muss sich nicht mit den \u00fcblichen Problemen rumschlagen, mit...<a class=\"readmore\" href=\"/studium/sozialpaedagogik/hsap-18124/bericht-17197\" title=\"Die Uni kann auch Spa\u00df machen :)\">\n&raquo; Erfahrungsbericht weiterlesen</a>\n", ""]], "studiengaenge": [["Sozialp\u00e4dagogik in der Ganztagsschule", "B.A."]]}